omnicloud/airport/__init__.py
omnicloud/airport/abc/__init__.py
omnicloud/airport/abc/_terminal.py
omnicloud/airport/terminals/__init__.py
omnicloud/airport/terminals/_dict/__init__.py
omnicloud/airport/terminals/_dict/_local/__init__.py
omnicloud/airport/terminals/_dict/_local/json.py
omnicloud/airport/terminals/_dict/_local/yaml.py
omnicloud/airport/tools/__init__.py
omnicloud/airport/tools/dict.py
omnicloud/airport/tools/files.py
omnicloud/airport/tools/json.py
omnicloud/airport/tools/pkg.py
omnicloud/airport/tools/type.py
omnicloud/airport/tools/yaml.py
omnicloud_airport-0.0.2.dist-info/LICENSE
omnicloud_airport-0.0.2.dist-info/METADATA
omnicloud_airport-0.0.2.dist-info/WHEEL
omnicloud_airport-0.0.2.dist-info/RECORD
