Metadata-Version: 2.1
Name: omnicloud-airport
Version: 0.0.2
Summary: platform for interacting with omnicloud
Home-page: https://omnicloud.world/airport
Keywords: omnicloud,supercloud,multicloud,cloud computing,migration
Author: Iurii Tarasenko
Author-email: iurii@omnicloud.world
Requires-Python: >=3.10,<4.0
Classifier: Intended Audience :: Developers
Classifier: Intended Audience :: Information Technology
Classifier: License :: OSI Approved :: MIT License
Classifier: Programming Language :: Python :: 3
Classifier: Programming Language :: Python :: 3.10
Classifier: Programming Language :: Python :: 3.11
Classifier: Programming Language :: Python :: 3.10
Classifier: Topic :: Software Development :: Libraries :: Python Modules
Requires-Dist: pyyaml (>=6.0,<7.0)
Requires-Dist: update (>=0.0.1,<0.0.2)
Project-URL: Documentation, https://docs.omnicloud.world/py-airport
Project-URL: Repository, https://github.com/omnicloudworld/py.airport
